{"regions": [{"name": "Arecibo", "totalClients": 177369, "totalClientsWithoutService": 1296, "totalClientsWithService": 176073, "totalClientsAffectedByPlannedOutage": 237, "totalClientsAffectedByLoadShed": 0, "percentageClientsWithoutService": 0.73, "percentageClientsWithService": 99.27}, {"name": "Bayamon", "totalClients": 216496, "totalClientsWithoutService": 1388, "totalClientsWithService": 215108, "totalClientsAffectedByPlannedOutage": 600, "totalClientsAffectedByLoadShed": 0, "percentageClientsWithoutService": 0.64, "percentageClientsWithService": 99.36}, {"name": "Carolina", "totalClients": 141663, "totalClientsWithoutService": 650, "totalClientsWithService": 141013, "totalClientsAffectedByPlannedOutage": 636, "totalClientsAffectedByLoadShed": 0, "percentageClientsWithoutService": 0.46, "percentageClientsWithService": 99.54}, {"name": "Caguas", "totalClients": 250514, "totalClientsWithoutService": 2204, "totalClientsWithService": 248310, "totalClientsAffectedByPlannedOutage": 1192, "totalClientsAffectedByLoadShed": 0, "percentageClientsWithoutService": 0.88, "percentageClientsWithService": 99.12}, {"name": "Mayaguez", "totalClients": 216605, "totalClientsWithoutService": 1661, "totalClientsWithService": 214944, "totalClientsAffectedByPlannedOutage": 955, "totalClientsAffectedByLoadShed": 0, "percentageClientsWithoutService": 0.77, "percentageClientsWithService": 99.23}, {"name": "Ponce", "totalClients": 212508, "totalClientsWithoutService": 623, "totalClientsWithService": 211885, "totalClientsAffectedByPlannedOutage": 0, "totalClientsAffectedByLoadShed": 0, "percentageClientsWithoutService": 0.29, "percentageClientsWithService": 99.71}, {"name": "San Juan", "totalClients": 253068, "totalClientsWithoutService": 376, "totalClientsWithService": 252692, "totalClientsAffectedByPlannedOutage": 133, "totalClientsAffectedByLoadShed": 0, "percentageClientsWithoutService": 0.15, "percentageClientsWithService": 99.85}], "totals": {"totalClientsWithoutService": 8198, "totalClientsAffectedByLoadShed": 0, "totalClients": 1468223, "totalClientsWithService": 1460025, "totalPercentageWithoutService": 0.56, "totalClientsAffectedByPlannedOutage": 3753, "totalPercentageWithService": 99.44}, "timestamp": "04/21/2026 11:00 AM"}