{"regions": [{"name": "Arecibo", "totalClients": 177369, "totalClientsWithoutService": 1215, "totalClientsWithService": 176154, "totalClientsAffectedByPlannedOutage": 832, "totalClientsAffectedByLoadShed": 0, "percentageClientsWithoutService": 0.69, "percentageClientsWithService": 99.31}, {"name": "Bayamon", "totalClients": 216496, "totalClientsWithoutService": 2292, "totalClientsWithService": 214204, "totalClientsAffectedByPlannedOutage": 1793, "totalClientsAffectedByLoadShed": 0, "percentageClientsWithoutService": 1.06, "percentageClientsWithService": 98.94}, {"name": "Carolina", "totalClients": 141663, "totalClientsWithoutService": 67, "totalClientsWithService": 141596, "totalClientsAffectedByPlannedOutage": 0, "totalClientsAffectedByLoadShed": 0, "percentageClientsWithoutService": 0.05, "percentageClientsWithService": 99.95}, {"name": "Caguas", "totalClients": 250514, "totalClientsWithoutService": 3231, "totalClientsWithService": 247283, "totalClientsAffectedByPlannedOutage": 2831, "totalClientsAffectedByLoadShed": 0, "percentageClientsWithoutService": 1.29, "percentageClientsWithService": 98.71}, {"name": "Mayaguez", "totalClients": 216605, "totalClientsWithoutService": 1483, "totalClientsWithService": 215122, "totalClientsAffectedByPlannedOutage": 312, "totalClientsAffectedByLoadShed": 0, "percentageClientsWithoutService": 0.68, "percentageClientsWithService": 99.32}, {"name": "Ponce", "totalClients": 212508, "totalClientsWithoutService": 1660, "totalClientsWithService": 210848, "totalClientsAffectedByPlannedOutage": 1524, "totalClientsAffectedByLoadShed": 0, "percentageClientsWithoutService": 0.78, "percentageClientsWithService": 99.22}, {"name": "San Juan", "totalClients": 253068, "totalClientsWithoutService": 2333, "totalClientsWithService": 250735, "totalClientsAffectedByPlannedOutage": 2044, "totalClientsAffectedByLoadShed": 0, "percentageClientsWithoutService": 0.92, "percentageClientsWithService": 99.08}], "totals": {"totalClientsWithoutService": 12281, "totalClientsAffectedByLoadShed": 0, "totalClients": 1468223, "totalClientsWithService": 1455942, "totalPercentageWithoutService": 0.84, "totalClientsAffectedByPlannedOutage": 9336, "totalPercentageWithService": 99.16}, "timestamp": "04/15/2026 12:00 PM"}